README.md
setup.cfg
setup.py
src/sdj_toolbox/__init__.py
src/sdj_toolbox/booleans.py
src/sdj_toolbox/cipher.py
src/sdj_toolbox/decorators.py
src/sdj_toolbox.egg-info/PKG-INFO
src/sdj_toolbox.egg-info/SOURCES.txt
src/sdj_toolbox.egg-info/dependency_links.txt
src/sdj_toolbox.egg-info/top_level.txt