Metadata-Version: 2.1
Name: sdj-toolbox
Version: 0.3.0
Summary: UNKNOWN
Home-page: https://gitea.irisib.be/sdejongh/sdj_toolbox.git
Author: Steve De Jongh
Author-email: dejongh.st@gmail.com
License: MIT
Keywords: python toolbox helpers
Platform: UNKNOWN
